{"location":{"localtime":"2019-08-28 0:45","country":"Denmark","localtime_epoch":1566945902,"name":"Copenhagen","lon":12.58,"region":"Hovedstaden","lat":55.67,"tz_id":"Europe/Copenhagen"},"forecast":{"forecastday":[{"date":"2019-08-21","astro":{"moonset":"12:06 PM","moon_illumination":"57","sunrise":"05:53 AM","moon_phase":"Waning Gibbous","sunset":"08:32 PM","moonrise":"10:43 PM"},"date_epoch":1566345600,"hour":[],"day":{"avgvis_km":9.9,"uv":0,"avgtemp_f":63,"avgtemp_c":17.2,"maxtemp_c":18,"maxtemp_f":64.4,"mintemp_c":15.5,"avgvis_miles":6,"mintemp_f":59.9,"totalprecip_in":0.03,"avghumidity":70,"condition":{"code":1063,"icon":"//cdn.apixu.com/weather/64x64/day/176.png","text":"Patchy rain possible"},"maxwind_kph":20.5,"maxwind_mph":12.8,"totalprecip_mm":0.7}}]}}
{"location":{"localtime":"2019-08-28 0:45","country":"Denmark","localtime_epoch":1566945902,"name":"Copenhagen","lon":12.58,"region":"Hovedstaden","lat":55.67,"tz_id":"Europe/Copenhagen"},"forecast":{"forecastday":[{"date":"2019-08-22","astro":{"moonset":"01:19 PM","moon_illumination":"49","sunrise":"05:55 AM","moon_phase":"Last Quarter","sunset":"08:29 PM","moonrise":"11:01 PM"},"date_epoch":1566432000,"hour":[],"day":{"avgvis_km":10,"uv":0,"avgtemp_f":64.5,"avgtemp_c":18.1,"maxtemp_c":19.3,"maxtemp_f":66.7,"mintemp_c":16.2,"avgvis_miles":6,"mintemp_f":61.2,"totalprecip_in":0,"avghumidity":72,"condition":{"code":1003,"icon":"//cdn.apixu.com/weather/64x64/day/116.png","text":"Partly cloudy"},"maxwind_kph":26.6,"maxwind_mph":16.6,"totalprecip_mm":0}}]}}
{"location":{"localtime":"2019-08-28 0:45","country":"Denmark","localtime_epoch":1566945904,"name":"Copenhagen","lon":12.58,"region":"Hovedstaden","lat":55.67,"tz_id":"Europe/Copenhagen"},"forecast":{"forecastday":[{"date":"2019-08-23","astro":{"moonset":"02:33 PM","moon_illumination":"42","sunrise":"05:57 AM","moon_phase":"Last Quarter","sunset":"08:27 PM","moonrise":"11:23 PM"},"date_epoch":1566518400,"hour":[],"day":{"avgvis_km":10,"uv":0,"avgtemp_f":67.9,"avgtemp_c":19.9,"maxtemp_c":21.1,"maxtemp_f":70,"mintemp_c":17.7,"avgvis_miles":6,"mintemp_f":63.9,"totalprecip_in":0,"avghumidity":71,"condition":{"code":1003,"icon":"//cdn.apixu.com/weather/64x64/day/116.png","text":"Partly cloudy"},"maxwind_kph":21.6,"maxwind_mph":13.4,"totalprecip_mm":0}}]}}
{"location":{"localtime":"2019-08-28 0:45","country":"Denmark","localtime_epoch":1566945905,"name":"Copenhagen","lon":12.58,"region":"Hovedstaden","lat":55.67,"tz_id":"Europe/Copenhagen"},"forecast":{"forecastday":[{"date":"2019-08-24","astro":{"moonset":"03:49 PM","moon_illumination":"35","sunrise":"05:58 AM","moon_phase":"Last Quarter","sunset":"08:24 PM","moonrise":"11:53 PM"},"date_epoch":1566604800,"hour":[],"day":{"avgvis_km":10,"uv":0,"avgtemp_f":68.9,"avgtemp_c":20.5,"maxtemp_c":22.1,"maxtemp_f":71.8,"mintemp_c":18.2,"avgvis_miles":6,"mintemp_f":64.8,"totalprecip_in":0,"avghumidity":77,"condition":{"code":1003,"icon":"//cdn.apixu.com/weather/64x64/day/116.png","text":"Partly cloudy"},"maxwind_kph":10.1,"maxwind_mph":6.3,"totalprecip_mm":0}}]}}
{"location":{"localtime":"2019-08-28 0:45","country":"Denmark","localtime_epoch":1566945906,"name":"Copenhagen","lon":12.58,"region":"Hovedstaden","lat":55.67,"tz_id":"Europe/Copenhagen"},"forecast":{"forecastday":[{"date":"2019-08-25","astro":{"moonset":"05:01 PM","moon_illumination":"28","sunrise":"06:00 AM","moon_phase":"Last Quarter","sunset":"08:22 PM","moonrise":"No moonrise"},"date_epoch":1566691200,"hour":[],"day":{"avgvis_km":10,"uv":0,"avgtemp_f":70,"avgtemp_c":21.1,"maxtemp_c":22.2,"maxtemp_f":72,"mintemp_c":18.5,"avgvis_miles":6,"mintemp_f":65.3,"totalprecip_in":0,"avghumidity":72,"condition":{"code":1000,"icon":"//cdn.apixu.com/weather/64x64/day/113.png","text":"Sunny"},"maxwind_kph":19.8,"maxwind_mph":12.3,"totalprecip_mm":0}}]}}
{"location":{"localtime":"2019-08-28 0:45","country":"Denmark","localtime_epoch":1566945907,"name":"Copenhagen","lon":12.58,"region":"Hovedstaden","lat":55.67,"tz_id":"Europe/Copenhagen"},"forecast":{"forecastday":[{"date":"2019-08-26","astro":{"moonset":"06:07 PM","moon_illumination":"20","sunrise":"06:02 AM","moon_phase":"Waning Crescent","sunset":"08:19 PM","moonrise":"12:33 AM"},"date_epoch":1566777600,"hour":[],"day":{"avgvis_km":10,"uv":0,"avgtemp_f":71.1,"avgtemp_c":21.7,"maxtemp_c":23.1,"maxtemp_f":73.6,"mintemp_c":19.1,"avgvis_miles":6,"mintemp_f":66.4,"totalprecip_in":0,"avghumidity":71,"condition":{"code":1003,"icon":"//cdn.apixu.com/weather/64x64/day/116.png","text":"Partly cloudy"},"maxwind_kph":18.7,"maxwind_mph":11.6,"totalprecip_mm":0}}]}}
{"location":{"localtime":"2019-08-28 0:45","country":"Denmark","localtime_epoch":1566945908,"name":"Copenhagen","lon":12.58,"region":"Hovedstaden","lat":55.67,"tz_id":"Europe/Copenhagen"},"forecast":{"forecastday":[{"date":"2019-08-27","astro":{"moonset":"07:01 PM","moon_illumination":"13","sunrise":"06:04 AM","moon_phase":"Waning Crescent","sunset":"08:17 PM","moonrise":"01:29 AM"},"date_epoch":1566864000,"hour":[],"day":{"avgvis_km":9.8,"uv":0,"avgtemp_f":71.6,"avgtemp_c":22,"maxtemp_c":23.2,"maxtemp_f":73.8,"mintemp_c":19.1,"avgvis_miles":6,"mintemp_f":66.4,"totalprecip_in":0.07,"avghumidity":77,"condition":{"code":1063,"icon":"//cdn.apixu.com/weather/64x64/day/176.png","text":"Patchy rain possible"},"maxwind_kph":24.8,"maxwind_mph":15.4,"totalprecip_mm":1.7}}]}}
